LICENSE
MANIFEST.in
README.md
pyproject.toml
requirements.txt
setup.py
pydis/__init__.py
pydis/__main__.py
pydis/abc.py
pydis/activity.py
pydis/appinfo.py
pydis/asset.py
pydis/audit_logs.py
pydis/automod.py
pydis/backoff.py
pydis/channel.py
pydis/client.py
pydis/colour.py
pydis/components.py
pydis/context_managers.py
pydis/embeds.py
pydis/emoji.py
pydis/enums.py
pydis/errors.py
pydis/file.py
pydis/flags.py
pydis/gateway.py
pydis/guild.py
pydis/http.py
pydis/integrations.py
pydis/interactions.py
pydis/invite.py
pydis/member.py
pydis/mentions.py
pydis/message.py
pydis/mixins.py
pydis/object.py
pydis/oggparse.py
pydis/opus.py
pydis/partial_emoji.py
pydis/permissions.py
pydis/player.py
pydis/raw_models.py
pydis/reaction.py
pydis/role.py
pydis/scheduled_event.py
pydis/shard.py
pydis/stage_instance.py
pydis/state.py
pydis/sticker.py
pydis/team.py
pydis/template.py
pydis/threads.py
pydis/user.py
pydis/utils.py
pydis/voice_client.py
pydis/welcome_screen.py
pydis/widget.py
pydis/app_commands/__init__.py
pydis/app_commands/checks.py
pydis/app_commands/commands.py
pydis/app_commands/errors.py
pydis/app_commands/models.py
pydis/app_commands/namespace.py
pydis/app_commands/transformers.py
pydis/app_commands/translator.py
pydis/app_commands/tree.py
pydis/easy/commands/__init__.py
pydis/easy/commands/_types.py
pydis/easy/commands/bot.py
pydis/easy/commands/cog.py
pydis/easy/commands/context.py
pydis/easy/commands/converter.py
pydis/easy/commands/cooldowns.py
pydis/easy/commands/core.py
pydis/easy/commands/errors.py
pydis/easy/commands/flags.py
pydis/easy/commands/help.py
pydis/easy/commands/hybrid.py
pydis/easy/commands/parameters.py
pydis/easy/commands/view.py
pydis/easy/tasks/__init__.py
pydis/types/__init__.py
pydis/types/activity.py
pydis/types/appinfo.py
pydis/types/audit_log.py
pydis/types/automod.py
pydis/types/channel.py
pydis/types/command.py
pydis/types/components.py
pydis/types/embed.py
pydis/types/emoji.py
pydis/types/gateway.py
pydis/types/guild.py
pydis_discord.egg-info/PKG-INFO
pydis_discord.egg-info/SOURCES.txt
pydis_discord.egg-info/dependency_links.txt
pydis_discord.egg-info/requires.txt
pydis_discord.egg-info/top_level.txt