Metadata-Version: 2.1
Name: pydis-discord
Version: 1.0.0
Summary: An Discord API v10 wrapper for Python 3
Home-page: https://github.com/RinkaGI/Pydis
Author: RinkaDev
Author-email: rinkadevoficial@gmail.com
Project-URL: Bug Reports, https://github.com/RinkaGI/Pydis/issues
Project-URL: Source, https://github.com/RinkaGI/Pydis/
Keywords: sample,setuptools,development,discord,bot,wrapper,api,modern,easy,fast
Classifier: Development Status :: 4 - Beta
Classifier: Intended Audience :: Developers
Classifier: Topic :: Software Development :: Build Tools
Classifier: License :: OSI Approved :: MIT License
Classifier: Programming Language :: Python :: 3
Classifier: Programming Language :: Python :: 3.7
Classifier: Programming Language :: Python :: 3.8
Classifier: Programming Language :: Python :: 3.9
Classifier: Programming Language :: Python :: 3.10
Classifier: Programming Language :: Python :: 3 :: Only
Requires-Python: >=3.8, <4
Provides-Extra: voice
Provides-Extra: docs
Provides-Extra: speed
Provides-Extra: test
License-File: LICENSE
